shapefile_to_GRP/GRP_class.py
shapefile_to_GRP/__init__.py
shapefile_to_GRP/box_class.py
shapefile_to_GRP/excavation_class.py
shapefile_to_GRP/grid_class.py
shapefile_to_GRP/model_class.py
shapefile_to_GRP/shaft_class.py
shapefile_to_GRP/tunnel_class.py
shapefile_to_GRP/wall_class.py
shapefile_to_GRP-0.0.4.dist-info/LICENSE
shapefile_to_GRP-0.0.4.dist-info/METADATA
shapefile_to_GRP-0.0.4.dist-info/WHEEL
shapefile_to_GRP-0.0.4.dist-info/top_level.txt
shapefile_to_GRP-0.0.4.dist-info/RECORD
