Metadata-Version: 2.1
Name: shapefile-to-GRP
Version: 0.0.4
Summary: A package to process shapefiles into GRP input files.
Home-page: https://github.com/mottmacdonaldglobal/shapefile_to_GRP_input
Author: Michael Crisp
Author-email: michael.crisp@mottmac.com
License: UNKNOWN
Project-URL: Bug Tracker, https://github.com/mottmacdonaldglobal/shapefile_to_GRP_input/issues
Platform: UNKNOWN
Classifier: Programming Language :: Python :: 3
Classifier: License :: OSI Approved :: MIT License
Classifier: Operating System :: OS Independent
Requires-Python: >=3.6
License-File: LICENSE
Requires-Dist: geopandas
Requires-Dist: numpy
Requires-Dist: pandas
Requires-Dist: Shapely
